snetcr/__init__.py
snetcr/_version.py
snetcr/analysis.py
snetcr/background.py
snetcr/datasets.py
snetcr/distance.py
snetcr/encoding.py
snetcr/export.py
snetcr/indexing.py
snetcr/neighbors.py
snetcr/pgen.py
snetcr/readers.py
snetcr/repertoire.py
snetcr/run_pipeline.py
snetcr/tools.py
snetcr/viz.py
snetcr/constants/__init__.py
snetcr/constants/base.py
snetcr/constants/datasets.py
snetcr/constants/distance.py
snetcr/constants/distributions.py
snetcr/constants/hashing.py
snetcr/constants/parsing.py
snetcr/constants/preprocessing.py
snetcr/constants/tools.py
snetcr/constants/data/adaptive_imgt_mapping.csv
snetcr/constants/data/adaptive_v_fam_to_imgt_gene.txt
snetcr/constants/data/alphabeta_db.tsv
snetcr/constants/data/combo_xcr.tsv
snetcr/constants/data/imgt_reference.tsv
snetcr/constants/data/vgene_to_cdr.txt
snetcr/constants/data/vdjdb/LICENSE.txt
snetcr/constants/data/vdjdb/cluster_members.txt
snetcr/constants/data/vdjdb/latest-version.txt
snetcr/constants/data/vdjdb/motif_pwms.txt
snetcr/constants/data/vdjdb/vdjdb.meta.txt
snetcr/constants/data/vdjdb/vdjdb.slim.meta.txt
snetcr/constants/data/vdjdb/vdjdb.slim.txt
snetcr/constants/data/vdjdb/vdjdb.txt
snetcr/constants/data/vdjdb/vdjdb_full.txt
snetcr/constants/data/vdjdb/vdjdb_human.txt
snetcr/constants/data/vdjdb/vdjdb_mouse.txt
snetcr/constants/modules/clustermap/exception.py
snetcr/constants/modules/clustermap/heatmap.py
snetcr/constants/modules/olga/__init__.py
snetcr/constants/modules/olga/compute_pgen.py
snetcr/constants/modules/olga/generate_sequences.py
snetcr/constants/modules/olga/generation_probability.py
snetcr/constants/modules/olga/load_model.py
snetcr/constants/modules/olga/olga_directed.py
snetcr/constants/modules/olga/preprocess_generative_model_and_data.py
snetcr/constants/modules/olga/sequence_generation.py
snetcr/constants/modules/olga/utils.py
snetcr/constants/modules/olga/__pycache__/__init__.cpython-39.pyc
snetcr/constants/modules/olga/__pycache__/generation_probability.cpython-39.pyc
snetcr-0.1.4.dist-info/LICENSE
snetcr-0.1.4.dist-info/METADATA
snetcr-0.1.4.dist-info/WHEEL
snetcr-0.1.4.dist-info/entry_points.txt
snetcr-0.1.4.dist-info/top_level.txt
snetcr-0.1.4.dist-info/RECORD
